{
  "equity": {
    "as_of": "2026-06-25 18:35:17",
    "cash_eur": 4201.99,
    "cash_usd": 4768.49,
    "fx_rate": 0.8812,
    "open_positions": 5,
    "positions_value_eur": 87460.09,
    "positions_value_usd": 99251.13,
    "source": "paper",
    "total_eur": 91671.31,
    "total_usd": 104030.08
  },
  "git": {
    "branch": "main",
    "commit": "5c4b8f02",
    "dirty": true
  },
  "hardware": {
    "cpu_temp_c": 68.3,
    "disk_pct": 48,
    "load_1min": 0.07,
    "mem_pct": 57
  },
  "last_runs": {
    "run_strategy": "Thu 2026-06-25 21:00:11 CEST",
    "sync_positions": "Thu 2026-06-25 20:35:18 CEST",
    "track_outcomes": "Thu 2026-06-25 02:32:29 CEST"
  },
  "predictions": {
    "correct": 15179,
    "incorrect": 2495,
    "last_24h": 7,
    "last_7d": 7044,
    "pending": 715,
    "total": 59776
  },
  "services": {
    "auto-pull": "active",
    "outcomes": "active",
    "status-push": "active",
    "strategy": "active",
    "sync": "active"
  },
  "timestamp_utc": "2026-06-25T19:10:30"
}
