{
  "equity": {
    "as_of": "2026-05-13 16:35:03",
    "cash_eur": 39400.2,
    "cash_usd": 46282.39,
    "fx_rate": 0.8513,
    "open_positions": 23,
    "positions_value_eur": 46284.54,
    "positions_value_usd": 54369.24,
    "source": "paper",
    "total_eur": 85684.73,
    "total_usd": 100651.63
  },
  "git": {
    "branch": "main",
    "commit": "bb224841",
    "dirty": true
  },
  "hardware": {
    "cpu_temp_c": 58.4,
    "disk_pct": 30,
    "load_1min": 0.08,
    "mem_pct": 49
  },
  "last_runs": {
    "run_strategy": "Wed 2026-05-13 18:00:23 CEST",
    "score_portfolio": "Wed 2026-05-13 18:34:25 CEST",
    "sync_positions": "Wed 2026-05-13 18:35:04 CEST",
    "track_outcomes": null
  },
  "predictions": {
    "correct": 4800,
    "incorrect": 1089,
    "last_24h": 924,
    "last_7d": 6349,
    "pending": 7123,
    "total": 14181
  },
  "services": {
    "auto-pull": "active",
    "outcomes": "active",
    "score": "active",
    "status-push": "active",
    "strategy": "active",
    "sync": "active"
  },
  "timestamp_utc": "2026-05-13T17:19:04"
}
