{
  "equity": {
    "as_of": "2026-07-02 05:35:11",
    "cash_eur": 2141.64,
    "cash_usd": 2439.22,
    "fx_rate": 0.878,
    "open_positions": 5,
    "positions_value_eur": 87342.7,
    "positions_value_usd": 99479.15,
    "source": "paper",
    "total_eur": 89484.33,
    "total_usd": 101918.37
  },
  "git": {
    "branch": "main",
    "commit": "1f7b379a",
    "dirty": true
  },
  "hardware": {
    "cpu_temp_c": 57.85,
    "disk_pct": 49,
    "load_1min": 0.1,
    "mem_pct": 66
  },
  "last_runs": {
    "run_strategy": "Wed 2026-07-01 21:00:17 CEST",
    "sync_positions": "Thu 2026-07-02 07:35:12 CEST",
    "track_outcomes": "Thu 2026-07-02 02:30:46 CEST"
  },
  "predictions": {
    "correct": 15306,
    "incorrect": 2636,
    "last_24h": 9,
    "last_7d": 52,
    "pending": 425,
    "total": 59821
  },
  "services": {
    "auto-pull": "active",
    "outcomes": "active",
    "status-push": "active",
    "strategy": "active",
    "sync": "active"
  },
  "timestamp_utc": "2026-07-02T05:36:10"
}
