{
  "equity": {
    "as_of": "2026-06-01 08:35:06",
    "cash_eur": 44076.69,
    "cash_usd": 51341.51,
    "fx_rate": 0.8585,
    "open_positions": 10,
    "positions_value_eur": 43545.72,
    "positions_value_usd": 50723.03,
    "source": "paper",
    "total_eur": 87622.41,
    "total_usd": 102064.54
  },
  "git": {
    "branch": "main",
    "commit": "a3fd96fc",
    "dirty": true
  },
  "hardware": {
    "cpu_temp_c": 63.35,
    "disk_pct": 37,
    "load_1min": 0.28,
    "mem_pct": 55
  },
  "last_runs": {
    "run_strategy": null,
    "score_portfolio": "Mon 2026-06-01 10:39:37 CEST",
    "sync_positions": "Mon 2026-06-01 10:35:07 CEST",
    "track_outcomes": "Mon 2026-06-01 02:32:40 CEST"
  },
  "predictions": {
    "correct": 14471,
    "incorrect": 2322,
    "last_24h": 1227,
    "last_7d": 8501,
    "pending": 1136,
    "total": 34896
  },
  "services": {
    "auto-pull": "active",
    "outcomes": "active",
    "score": "active",
    "status-push": "active",
    "strategy": "?",
    "sync": "active"
  },
  "timestamp_utc": "2026-06-01T08:42:34"
}
