{
  "equity": {
    "as_of": "2026-07-17 03:40:05",
    "cash_eur": 37406.69,
    "cash_usd": 42823.92,
    "fx_rate": 0.8735,
    "open_positions": 5,
    "positions_value_eur": 47597.31,
    "positions_value_usd": 54490.34,
    "source": "ai_swing",
    "total_eur": 85004.0,
    "total_usd": 97314.26
  },
  "git": {
    "branch": "main",
    "commit": "a63f1812",
    "dirty": false
  },
  "hardware": {
    "cpu_temp_c": 61.7,
    "disk_pct": 58,
    "load_1min": 0.01,
    "mem_pct": 41
  },
  "last_runs": {
    "run_strategy": "Thu 2026-07-16 21:00:10 CEST",
    "sync_positions": "Fri 2026-07-17 05:35:04 CEST",
    "track_outcomes": "Fri 2026-07-17 02:30:28 CEST"
  },
  "predictions": {
    "correct": 15328,
    "incorrect": 2637,
    "last_24h": 5,
    "last_7d": 40,
    "pending": 461,
    "total": 59925
  },
  "services": {
    "auto-pull": "active",
    "outcomes": "active",
    "status-push": "active",
    "strategy": "active",
    "sync": "active"
  },
  "timestamp_utc": "2026-07-17T04:18:34"
}
