{
  "equity": {
    "as_of": "2026-07-24 07:35:04",
    "cash_eur": 2142.85,
    "cash_usd": 2439.21,
    "fx_rate": 0.8785,
    "open_positions": 5,
    "positions_value_eur": 82798.85,
    "positions_value_usd": 94250.26,
    "source": "paper",
    "total_eur": 84941.69,
    "total_usd": 96689.47
  },
  "git": {
    "branch": "main",
    "commit": "3fb91479",
    "dirty": false
  },
  "hardware": {
    "cpu_temp_c": 60.6,
    "disk_pct": 59,
    "load_1min": 0.2,
    "mem_pct": 42
  },
  "last_runs": {
    "run_strategy": "Thu 2026-07-23 21:00:09 CEST",
    "sync_positions": "Fri 2026-07-24 09:35:04 CEST",
    "track_outcomes": "Fri 2026-07-24 02:30:17 CEST"
  },
  "predictions": {
    "correct": 15346,
    "incorrect": 2638,
    "last_24h": 5,
    "last_7d": 37,
    "pending": 469,
    "total": 59962
  },
  "services": {
    "auto-pull": "active",
    "outcomes": "active",
    "status-push": "active",
    "strategy": "active",
    "sync": "active"
  },
  "timestamp_utc": "2026-07-24T07:38:04"
}
