{
  "equity": {
    "as_of": "2026-06-26 08:35:12",
    "cash_eur": 4201.99,
    "cash_usd": 4768.49,
    "fx_rate": 0.8812,
    "open_positions": 5,
    "positions_value_eur": 86985.47,
    "positions_value_usd": 98712.52,
    "source": "paper",
    "total_eur": 91187.47,
    "total_usd": 103481.01
  },
  "git": {
    "branch": "main",
    "commit": "cd014392",
    "dirty": true
  },
  "hardware": {
    "cpu_temp_c": 64.45,
    "disk_pct": 49,
    "load_1min": 0.09,
    "mem_pct": 63
  },
  "last_runs": {
    "run_strategy": "Fri 2026-06-26 11:00:23 CEST",
    "sync_positions": "Fri 2026-06-26 10:35:13 CEST",
    "track_outcomes": "Fri 2026-06-26 02:32:22 CEST"
  },
  "predictions": {
    "correct": 15191,
    "incorrect": 2515,
    "last_24h": 11,
    "last_7d": 6334,
    "pending": 660,
    "total": 59780
  },
  "services": {
    "auto-pull": "active",
    "outcomes": "active",
    "status-push": "active",
    "strategy": "active",
    "sync": "active"
  },
  "timestamp_utc": "2026-06-26T09:28:56"
}
