{
  "equity": {
    "as_of": "2026-05-30 01:35:10",
    "cash_eur": 44102.49,
    "cash_usd": 51419.48,
    "fx_rate": 0.8577,
    "open_positions": 10,
    "positions_value_eur": 43328.52,
    "positions_value_usd": 50517.1,
    "source": "paper",
    "total_eur": 87431.01,
    "total_usd": 101936.58
  },
  "git": {
    "branch": "main",
    "commit": "8b9d6dc4",
    "dirty": true
  },
  "hardware": {
    "cpu_temp_c": 61.7,
    "disk_pct": 37,
    "load_1min": 0.18,
    "mem_pct": 57
  },
  "last_runs": {
    "run_strategy": null,
    "score_portfolio": "Sat 2026-05-30 03:36:45 CEST",
    "sync_positions": "Sat 2026-05-30 03:35:11 CEST",
    "track_outcomes": "Sat 2026-05-30 02:30:22 CEST"
  },
  "predictions": {
    "correct": 14442,
    "incorrect": 2291,
    "last_24h": 1239,
    "last_7d": 8224,
    "pending": 779,
    "total": 32083
  },
  "services": {
    "auto-pull": "active",
    "outcomes": "active",
    "score": "active",
    "status-push": "active",
    "strategy": "?",
    "sync": "active"
  },
  "timestamp_utc": "2026-05-30T02:17:12"
}
