{
  "equity": {
    "as_of": "2026-06-23 04:35:22",
    "cash_eur": 43031.22,
    "cash_usd": 49319.45,
    "fx_rate": 0.8725,
    "open_positions": 15,
    "positions_value_eur": 45872.34,
    "positions_value_usd": 52575.74,
    "source": "paper",
    "total_eur": 88903.56,
    "total_usd": 101895.19
  },
  "git": {
    "branch": "main",
    "commit": "0f0b64dc",
    "dirty": true
  },
  "hardware": {
    "cpu_temp_c": 60.6,
    "disk_pct": 44,
    "load_1min": 0.34,
    "mem_pct": 62
  },
  "last_runs": {
    "run_strategy": "Mon 2026-06-22 21:00:30 CEST",
    "score_portfolio": "Tue 2026-06-23 06:40:16 CEST",
    "sync_positions": "Tue 2026-06-23 06:35:23 CEST",
    "track_outcomes": "Tue 2026-06-23 02:32:28 CEST"
  },
  "predictions": {
    "correct": 15149,
    "incorrect": 2472,
    "last_24h": 1281,
    "last_7d": 8942,
    "pending": 987,
    "total": 58205
  },
  "services": {
    "auto-pull": "active",
    "outcomes": "active",
    "score": "active",
    "status-push": "active",
    "strategy": "active",
    "sync": "active"
  },
  "timestamp_utc": "2026-06-23T05:02:50"
}
