{
  "equity": {
    "as_of": "2026-07-20 14:40:09",
    "cash_eur": 33146.03,
    "cash_usd": 37937.54,
    "fx_rate": 0.8737,
    "open_positions": 5,
    "positions_value_eur": 51918.7,
    "positions_value_usd": 59423.94,
    "source": "ai_swing",
    "total_eur": 85064.73,
    "total_usd": 97361.48
  },
  "git": {
    "branch": "main",
    "commit": "98d11613",
    "dirty": false
  },
  "hardware": {
    "cpu_temp_c": 62.8,
    "disk_pct": 58,
    "load_1min": 0.08,
    "mem_pct": 38
  },
  "last_runs": {
    "run_strategy": "Mon 2026-07-20 17:00:10 CEST",
    "sync_positions": "Mon 2026-07-20 16:35:07 CEST",
    "track_outcomes": "Mon 2026-07-20 02:30:23 CEST"
  },
  "predictions": {
    "correct": 15337,
    "incorrect": 2638,
    "last_24h": 5,
    "last_7d": 37,
    "pending": 463,
    "total": 59942
  },
  "services": {
    "auto-pull": "active",
    "outcomes": "active",
    "status-push": "active",
    "strategy": "active",
    "sync": "active"
  },
  "timestamp_utc": "2026-07-20T15:03:07"
}
