{
  "equity": {
    "as_of": "2026-05-18 16:35:17",
    "cash_eur": 35598.6,
    "cash_usd": 41369.67,
    "fx_rate": 0.8605,
    "open_positions": 23,
    "positions_value_eur": 50707.62,
    "positions_value_usd": 58928.09,
    "source": "paper",
    "total_eur": 86305.67,
    "total_usd": 100297.12
  },
  "git": {
    "branch": "main",
    "commit": "607b4372",
    "dirty": true
  },
  "hardware": {
    "cpu_temp_c": 64.45,
    "disk_pct": 31,
    "load_1min": 0.08,
    "mem_pct": 56
  },
  "last_runs": {
    "run_strategy": "Mon 2026-05-18 18:00:21 CEST",
    "score_portfolio": "Mon 2026-05-18 18:35:54 CEST",
    "sync_positions": "Mon 2026-05-18 18:35:17 CEST",
    "track_outcomes": "Mon 2026-05-18 02:46:28 CEST"
  },
  "predictions": {
    "correct": 8750,
    "incorrect": 1399,
    "last_24h": 1020,
    "last_7d": 6753,
    "pending": 7533,
    "total": 19011
  },
  "services": {
    "auto-pull": "active",
    "outcomes": "active",
    "score": "active",
    "status-push": "active",
    "strategy": "active",
    "sync": "active"
  },
  "timestamp_utc": "2026-05-18T16:57:41"
}
